py_ballisticcalc-stubs/__init__.pyi
py_ballisticcalc-stubs/atmosphere.pyi
py_ballisticcalc-stubs/drag.pyi
py_ballisticcalc-stubs/multiple_bc.pyi
py_ballisticcalc-stubs/profile.pyi
py_ballisticcalc-stubs/projectile.pyi
py_ballisticcalc-stubs/shot_parameters.pyi
py_ballisticcalc-stubs/trajectory_calculator.pyi
py_ballisticcalc-stubs/trajectory_data.pyi
py_ballisticcalc-stubs/weapon.pyi
py_ballisticcalc-stubs/wind.pyi
py_ballisticcalc-stubs/bmath/__init__.pyi
py_ballisticcalc-stubs/bmath/unit/__init__.pyi
py_ballisticcalc-stubs/bmath/unit/angular.pyi
py_ballisticcalc-stubs/bmath/unit/distance.pyi
py_ballisticcalc-stubs/bmath/unit/energy.pyi
py_ballisticcalc-stubs/bmath/unit/pressure.pyi
py_ballisticcalc-stubs/bmath/unit/temperature.pyi
py_ballisticcalc-stubs/bmath/unit/velocity.pyi
py_ballisticcalc-stubs/bmath/unit/weight.pyi
py_ballisticcalc-stubs/bmath/vector/__init__.pyi
py_ballisticcalc-stubs/bmath/vector/vector.pyi
py_ballisticcalc_stubs-1.0.9.2.dist-info/LICENSE
py_ballisticcalc_stubs-1.0.9.2.dist-info/METADATA
py_ballisticcalc_stubs-1.0.9.2.dist-info/WHEEL
py_ballisticcalc_stubs-1.0.9.2.dist-info/top_level.txt
py_ballisticcalc_stubs-1.0.9.2.dist-info/RECORD
