Metadata-Version: 2.1
Name: py-ballisticcalc-stubs
Version: 1.0.9.2
Summary: PEP561 stub files for the py_ballisticcalc library
Home-page: https://github.com/o-murphy/py_ballisticcalc-stubs
Author: o-murphy
Author-email: thehelixpg@gmail.com
Maintainer: o-murphy
Maintainer-email: thehelixpg@gmail.com
License: UNKNOWN
Platform: UNKNOWN
Requires-Python: >= 3.9
